Metadata-Version: 1.0
Name: FraudTransactionDetector
Version: 0.1.4
Summary: Scalable Fraud Transaction Identifier using Clustering, Anomaly Detection and Classification ML Algorithms
Home-page: http://pypi.python.org/pypi/FraudTransactionDetector/
Author: Venkata Siva Rama Sastry Kavuri
Author-email: sivaram.kavuri@gmail.com
License: License.txt
Platform: UNKNOWN
